oumnetwork/__init__.py
oumnetwork/crawling.py
oumnetwork/network.py
oumnetwork/node.py
oumnetwork/protocol.py
oumnetwork/routing.py
oumnetwork/storage.py
oumnetwork/utils.py
OUM_Network-0.0.3.dist-info/LICENSE
OUM_Network-0.0.3.dist-info/METADATA
OUM_Network-0.0.3.dist-info/WHEEL
OUM_Network-0.0.3.dist-info/top_level.txt
OUM_Network-0.0.3.dist-info/RECORD
