Metadata-Version: 2.1
Name: OUM-Network
Version: 0.0.3
Summary: OUM_Network is an implementation of Kademlia designed for decentralized AI.
Author-email: OumDev <you@example.com>
Classifier: Intended Audience :: Developers
Classifier: Operating System :: OS Independent
Classifier: Programming Language :: Python
Classifier: Programming Language :: Python :: 3
Classifier: Programming Language :: Python :: 3.5
Classifier: Programming Language :: Python :: 3.6
Classifier: Programming Language :: Python :: 3.7
Requires-Python: >=3.5
License-File: LICENSE
Requires-Dist: rpcudp >=4.0.1
